topsis_arpitjain_102203499/102203499_main (1).py
topsis_arpitjain_102203499/__init__.py
topsis_arpitjain_102203499-1.0.0.dist-info/METADATA
topsis_arpitjain_102203499-1.0.0.dist-info/WHEEL
topsis_arpitjain_102203499-1.0.0.dist-info/top_level.txt
topsis_arpitjain_102203499-1.0.0.dist-info/RECORD
